README.md
iambic/__init__.py
iambic/ast/__init__.py
iambic/ast/base.py
iambic/ast/index.py
iambic/ast/node.py
iambic/bin/__init__.py
iambic/bin/cli.py
iambic/parse/__init__.py
iambic/parse/data.py
iambic/parse/text.py
iambic/plays/__init__.py
iambic/plays/comedies/a-midsummer-night-s-dream.md
iambic/plays/comedies/as-you-like-it.md
iambic/plays/comedies/love-s-labours-lost.md
iambic/plays/comedies/much-ado-about-nothing.md
iambic/plays/comedies/the-comedy-of-errors.md
iambic/plays/comedies/the-merry-wives-of-windsor.md
iambic/plays/comedies/twelfth-night.md
iambic/plays/comedies/two-gentlemen-of-verona.md
iambic/plays/histories/edward-iii.md
iambic/plays/histories/henry-iv-part-1.md
iambic/plays/histories/henry-iv-part-2.md
iambic/plays/histories/henry-v.md
iambic/plays/histories/henry-vi-part-1.md
iambic/plays/histories/henry-vi-part-2.md
iambic/plays/histories/henry-vi-part-3.md
iambic/plays/histories/henry-viii.md
iambic/plays/histories/king-john.md
iambic/plays/histories/richard-ii.md
iambic/plays/histories/richard-iii.md
iambic/plays/problems/all-s-well-that-ends-well.md
iambic/plays/problems/measure-for-measure.md
iambic/plays/problems/the-merchant-of-venice.md
iambic/plays/problems/the-taming-of-the-shrew.md
iambic/plays/problems/troilus-and-cressida.md
iambic/plays/roman/antony-and-cleopatra.md
iambic/plays/roman/coriolanus.md
iambic/plays/roman/julius-caesar.md
iambic/plays/roman/titus-andronicus.md
iambic/plays/romances/a-winter-s-tale.md
iambic/plays/romances/cymbeline.md
iambic/plays/romances/pericles.md
iambic/plays/romances/the-tempest.md
iambic/plays/tragedies/hamlet.md
iambic/plays/tragedies/king-lear.md
iambic/plays/tragedies/macbeth.md
iambic/plays/tragedies/othello.md
iambic/plays/tragedies/romeo-and-juliet.md
iambic/plays/tragedies/timon-of-athens.md
iambic/render/__init__.py
iambic/render/html.py
iambic/render/json.py
iambic/render/markdown.py
iambic/render/table.py
iambic/roman.py
schema.json
iambic-3.0.0.dist-info/LICENSE
iambic-3.0.0.dist-info/METADATA
iambic-3.0.0.dist-info/WHEEL
iambic-3.0.0.dist-info/RECORD
