Metadata-Version: 2.1
Name: iambic
Version: 3.0.0
Summary: Data extraction and rendering library for Shakespearean text.
Home-page: https://github.com/seandstewart/iambic
License: MIT
Keywords: text,render,shakespeare,text-processing
Author: Sean Stewart
Author-email: sean_stewart@me.com
Requires-Python: >=3.11,<4.0
Classifier: Development Status :: 5 - Production/Stable
Classifier: Intended Audience :: Developers
Classifier: License :: OSI Approved :: MIT License
Classifier: Natural Language :: English
Classifier: Operating System :: OS Independent
Classifier: Programming Language :: Python
Classifier: Programming Language :: Python :: 3
Classifier: Programming Language :: Python :: 3.11
Classifier: Programming Language :: Python :: 3 :: Only
Classifier: Programming Language :: Python :: 3.6
Classifier: Programming Language :: Python :: 3.7
Classifier: Programming Language :: Python :: 3.8
Classifier: Programming Language :: Python :: Implementation :: CPython
Classifier: Topic :: Text Processing
Classifier: Topic :: Text Processing :: Indexing
Classifier: Topic :: Text Processing :: Linguistic
Classifier: Topic :: Text Processing :: Markup
Classifier: Topic :: Text Processing :: Markup :: HTML
Classifier: Topic :: Utilities
Classifier: Typing :: Typed
Requires-Dist: html2text (>=2020.1.16,<2021.0.0)
Requires-Dist: markdown (>=3,<4)
Requires-Dist: pymdown-extensions (>=10,<11)
Requires-Dist: tabulate (>=0.8.9,<0.9.0)
Requires-Dist: typical (>=2,<3)
Requires-Dist: ujson (>=5,<6)
Project-URL: Repository, https://github.com/seandstewart/iambic
